ai_security_deprecated/__init__.py
ai_security_deprecated/cli.py
ai_security_cli-1.0.1.dist-info/METADATA
ai_security_cli-1.0.1.dist-info/WHEEL
ai_security_cli-1.0.1.dist-info/entry_points.txt
ai_security_cli-1.0.1.dist-info/top_level.txt
ai_security_cli-1.0.1.dist-info/RECORD
