Metadata-Version: 2.4
Name: ai-security-cli
Version: 1.0.1
Summary: DEPRECATED - Please use 'aisentry' instead. pip install aisentry
Author: AISentry Team
License-Expression: MIT
Project-URL: Homepage, https://aisentry.co
Project-URL: Repository, https://github.com/deosha/aisentry
Keywords: deprecated,aisentry
Classifier: Development Status :: 7 - Inactive
Classifier: Intended Audience :: Developers
Classifier: Topic :: Security
Requires-Python: >=3.8
Requires-Dist: aisentry>=1.0.0b1
